tests/__init__.py
tests/test_integration.py
numint-0.1.0.dist-info/LICENSE
numint-0.1.0.dist-info/METADATA
numint-0.1.0.dist-info/WHEEL
numint-0.1.0.dist-info/top_level.txt
numint-0.1.0.dist-info/RECORD
